CHANGES.txt
CONTRIBUTORS.txt
README.txt
bootstrap.py
buildout.cfg
setup.cfg
setup.py
koansys/__init__.py
koansys.recipe.pybsddb.egg-info/PKG-INFO
koansys.recipe.pybsddb.egg-info/SOURCES.txt
koansys.recipe.pybsddb.egg-info/dependency_links.txt
koansys.recipe.pybsddb.egg-info/entry_points.txt
koansys.recipe.pybsddb.egg-info/namespace_packages.txt
koansys.recipe.pybsddb.egg-info/not-zip-safe
koansys.recipe.pybsddb.egg-info/requires.txt
koansys.recipe.pybsddb.egg-info/top_level.txt
koansys/recipe/__init__.py
koansys/recipe/pybsddb/README.txt
koansys/recipe/pybsddb/__init__.py
koansys/recipe/pybsddb/tests/__init__.py
koansys/recipe/pybsddb/tests/test_docs.py