Metadata-Version: 1.0
Name: koansys.recipe.pybsddb
Version: 1.0.1
Summary: A recipe to build pybsddb
Home-page: http://koansys.com
Author: Koansys, LLC
Author-email: reed@koansys.com
License: BSD
Keywords: recipe buildout bdb
Platform: UNKNOWN
Classifier: Framework :: Buildout
Classifier: Intended Audience :: Developers
Classifier: Topic :: Software Development :: Build Tools
Classifier: Topic :: Software Development :: Libraries :: Python Modules
Classifier: License :: OSI Approved :: BSD License
